dfcon/__init__.py
dfcon/directory.py
dfcon/path_filter.py
dfcon-0.3.0.dist-info/LICENSE
dfcon-0.3.0.dist-info/METADATA
dfcon-0.3.0.dist-info/WHEEL
dfcon-0.3.0.dist-info/top_level.txt
dfcon-0.3.0.dist-info/RECORD
