Metadata-Version: 2.1
Name: dfcon
Version: 0.3.0
Summary: To make access to the database easier.
Home-page: https://github.com/MTamon/dataFileController.git
Author: Tamon Mikawa
Author-email: mtamon.engineering@gmail.com
License: MIT License
Keywords: DataSet,File-Search,File-Controle
Classifier: Development Status :: 4 - Beta
Classifier: License :: OSI Approved :: MIT License
Classifier: Programming Language :: Python
Classifier: Programming Language :: Python :: 3
Classifier: Programming Language :: Python :: 3.9
Classifier: Topic :: Database
Classifier: Topic :: Software Development :: Libraries :: Python Modules
License-File: LICENSE
Requires-Dist: cmpfilter
